{
    "logs": [
        {
            "outputFile": "C:\\Users\\Ryan Warwick\\Documents\\Team YAT\\app\\build\\intermediates\\incremental\\mergeDebugResources\\merged.dir\\values-v16\\values-v16.xml",
            "map": [
                {
                    "source": "C:\\Users\\Ryan Warwick\\.gradle\\caches\\transforms-1\\files-1.1\\support-compat-26.1.0.aar\\fba934187caec76aae0b2bf44f81db10\\res\\values-v16\\values-v16.xml",
                    "from": {
                        "startLines": "2",
                        "startColumns": "4",
                        "startOffsets": "55",
                        "endColumns": "65",
                        "endOffsets": "116"
                    }
                },
                {
                    "source": "C:\\Users\\Ryan Warwick\\.gradle\\caches\\transforms-1\\files-1.1\\appcompat-v7-26.1.0.aar\\65d684fcfe90ffa9e7a5dc94d29b14cb\\res\\values-v16\\values-v16.xml",
                    "from": {
                        "startLines": "2",
                        "startColumns": "4",
                        "startOffsets": "55",
                        "endLines": "5",
                        "endColumns": "12",
                        "endOffsets": "223"
                    },
                    "to": {
                        "startLines": "3",
                        "startColumns": "4",
                        "startOffsets": "121",
                        "endLines": "6",
                        "endColumns": "12",
                        "endOffsets": "289"
                    }
                }
            ]
        }
    ]
}